pymt_dbseabed/__init__.py
pymt_dbseabed/bmi.py
pymt_dbseabed/data/DbSeabedData/api.yaml
pymt_dbseabed/data/DbSeabedData/config.yaml
pymt_dbseabed/data/DbSeabedData/info.yaml
pymt_dbseabed/data/DbSeabedData/parameters.yaml
pymt_dbseabed/data/DbSeabedData/run.yaml
pymt_dbseabed-0.1.0.dist-info/LICENSE
pymt_dbseabed-0.1.0.dist-info/METADATA
pymt_dbseabed-0.1.0.dist-info/WHEEL
pymt_dbseabed-0.1.0.dist-info/entry_points.txt
pymt_dbseabed-0.1.0.dist-info/top_level.txt
pymt_dbseabed-0.1.0.dist-info/RECORD
